{
  "display": {
    "icon": {
      "id": "minecraft:netherite_block"
    },
    "title": {
      "translate": "advancements.creator.title"
    },
    "description": {
      "translate": "advancements.creator.descr"
    },
    "frame": "challenge",
    "show_toast": true,
    "announce_to_chat": true,
    "hidden": true
  },
  "criteria": {
    "creator_0": {
      "trigger": "minecraft:impossible"
    }
  },
  "rewards": {
    "experience": 100
  },
  "parent": "charming_chisels:chiseled_jawline"
}